cfdpy/__init__.py
cfdpy/advection.py
cfdpy/burgers.py
cfdpy/channel.py
cfdpy/poisson.py
cfdpy/derivative/__init__.py
cfdpy/derivative/finiteDifferenceMethods.py
cfdpy/derivative/spectralMethods.py
cfdpy/integrate/RungeKuttaMethods.py
cfdpy/integrate/__init__.py
cfdpy/integrate/lowStorageRungeKuttaMethods.py
cfdpy/utils/__init__.py
cfdpy/utils/grid.py
cfdpy/utils/wallLaw.py
cfdpy-0.0.1.dist-info/LICENSE
cfdpy-0.0.1.dist-info/METADATA
cfdpy-0.0.1.dist-info/WHEEL
cfdpy-0.0.1.dist-info/top_level.txt
cfdpy-0.0.1.dist-info/RECORD
