Metadata-Version: 2.1
Name: cfdpy
Version: 0.0.1
Summary: Computational Fluid Dynamics for Python
Home-page: https://github.com/mkihara/cfdpy
Author: Mizuki KIHARA
Author-email: mkihara@users.noreply.github.com
Project-URL: Bug Tracker, https://github.com/mkihara/cfdpy/issues
Classifier: Programming Language :: Python :: 3
Classifier: License :: OSI Approved :: MIT License
Classifier: Operating System :: OS Independent
Requires-Python: >=3.10
License-File: LICENSE
Requires-Dist: numpy (>=1.22)
Requires-Dist: scipy (>=1.7)
